{
    "confirm":"OK",
    "weiqundezhou":"Nicehand(Nicehand)",
    "my_group":"My Club",
    "my_friend":"My Friends",
    "my_game":"My Games",
    "ignore":"Community",
    "user_setting":"User Settings",
    "username":"User Name",
    "game_setting":"Game Configurations",
    "user_head_image":"Icon",
    "language_setting":"Language Settings",
    "Four_color_deck":"Four color deck",
    "music_volume":"Music Volume",
    "effects_volume":"Effects Volume",
    "account_or_password_not_empty":"Both user name and password cannot be blank",
    "create_group":"Create Club",
    "search_group":"Search Club",
    "search_friend":"Search Player",
    "search":"Search",
    "input_group_name":"Club Name",
    "input_group_descrption":"Club Description",
    "group_note":"Group Notes",
    "add_group_user":"Add club User",
    "already_in_room":"Already in this room",
    "group_search_word":"          Please input club name",
    "friend_search_word":"          Please input player name or ID",
    "friend_local_search_word":"                             Search",
    "group_name_empty":"Club name cannot be blank",
    "input_password":"Please Input password",
    "cancel":"Cancel",
    "save":"Save",
    "back":"Back",
    "language":"Multi Language",
    "setting":"Settings",
    "connect_failed":"Network unavailable, please check WIFI or network.",
    "connect_failed_and_try":"Network unavailable, please check WIFI or network, try again...",
    "player_details":"Player Info",
    "connect_failed":"Cann't connect to server",
    "login":"Login",
    "switch_to_cellphone_login":"Use Cellphone Login",
    "switch_to_account_login":"Use Account Login",
    "register":"Register",
    "nickname_empty":"Nickname cannot be empty.",
    "roomname_empty":"Room name cannot be empty.",
    "username_empty":"User name cannot be empty.",
    "groupname_empty":"club name cannot be empty.",
    "password_empty":"Password cannot be empty.",
    "passowrd_confirm_empty":"Please input password again.",
    "passowrd_not_same":"Password does not match, please try again. ",
    "referer_Optional_":"Referer(Optional)",
    "cell_Optional":"Cell number(Optional)",
    "veri_code":"Verficiation code",
    "register_failed":"User name already exists, please try another.",
    "account":"Account: ",
    "password":"Password: ",
    "input_account":"Please input account name",
    "forgot_password":"Forgot password?",
    "input_account_name":"Please input acount name",
    "input_phone_number":"Please input phone number",
    "input_password_again":"Please input password again",
    "license1":"By clicking the registration above, you agree to the following:",
    "license2":"                                                      <Nicehand User License and Service Agreement>",
    "license3":"By using this software, you agree to the following:",
    "license4":"                                          <Nicehand User License and Service Agreement>",
    "Cell_number":"Cell Phone number:",
    "verfy_code":"Verification Number",
    "Invalid_cell":"cell number invalid",
    "get_verify_code":"Get verify code",
    "timeout":"Login Timeout",
    "key_not_found":"Login Key not found",
    "other_error":"Other Mistake",
    "already_login":"Already logged in",
    "recv_player_data_failed":"Failed to get player info",
    "click_into_room":"Click to enter room",
    "change_user_data_failed":"Failed to modify player info.",
    "change_user_nickname_failed":"Failed to modify player nickname",
    "edit_group_info_failed":"Failed to modify club info",
    "name":"Name",
    "sex":"Gender",
    "male":"Male",
    "female":"Female",
    "no_game_room":"Guys, Let's click the shiny button below, \n Create a homegame with number\n and ask friend to input the room number to play?",
    "no_game_room_in_club":"my friend, there is no game at this time.\nClick  + button right above \n and invite friends to play\n~~",
    "get_room_list_failed":"Failed to get room list",
    "holdempoker":"NL Hold'em Poker",
    "openfacechinesepoker":"OpenFace Poker",
    "pineapplepoker":"Pineapple Poker",
    "omaha":"PLO",
    "omaha_hl":"PLO High/Low",
    "mtt_holdempoker":"MTT NL Hold'em Poker",
    "mtt_omaha":"MTT PLO",
    "mtt_omaha_hl":"MTT PLO High/Low",
    "dezhoupuke":"Texas Holem",
    "Tournament":"Tournament",
    "game_2_type":"OpenFaceChinese Poker",
    "my_roos":"My room",
    "open":"Open",
    "close":"Closed",
    "property_name":"Property",
    "input_room_name":"Please input room name",
    "input_room_password":"Please input room password",
    "other_content":"Other Content",
    "create":"Create",
    "member_list_failed":"Failed to get club member list",
    "user_info_failed":"Failed to get player info",
    "create_room":"Create Room",
    "create_room_success":"Create room Success!",
    "create_room_failed":"Create room failed",
    "max_buy":"Max:",
    "min_buy":"Min:",
    "match_result":"Realtime score",
    "group_result":"club score",
    "my_result":"My scores",
    "Current_week_scores":"7 days",
    "Current_month_scores":"30 days",
    "nickname":"Nick Name",
    "buy_chip":"Buyin",
    "win_chip":"Profit",
    "text_room":"Room name",
    "pool":"Pot",
    "temporary_room":"Temporary Room",
    "Not_in_any_club":"Not In Any Club",
    "group_name":"Club Name",
    "group_password":"Club Password",
    "Invitation":"Invitation",
    "Address_book":"Address Book",
    "is_request_add_group":"Add Club?",
    "record_time_too_shop":"Record Time too short",
    "downloading":"Downloading...",
    "take_photo":"Take picture",
    "match_record":"Game Record",
    "hand_poker":"Hands",
    "winner":"Winner",
    "minest":"Min",
    "one_third":"Half Pot",
    "half_pool":"2/3 Pot",
    "full_pool":"Full Pot",
    "away":"Leave",
    "select_from_album":"Select from album",
    "dissolve_group":"Dismiss Club",
    "quit_group":"Delete and quit",
    "quit_group_owner":"Quit/Disband",
    "move_finger_cancel":"Slide up to cancel",
    "release_finger_cancel":"Release to cancel",
    "press_voice":"Press and send voice",
    "release_send":"Relase to send voice",
    "pre_step":"Previous",
    "next_step":"Next",
    "recv_error":"Error",
    "cannot_add_chip":"Cannot add chips",
    "clear_record":"Are you sure to clear chat records?",
    "clear_record_text":"Clear chat record",
    "goto_new_room":"Go to new room",
    "credit_not_enough":"Not enough credit, please contact club manager.",
    "max_chip":"Your chips has reached max number, cann't add",
    "logout":"Logout",
    "share":"Share and receive gift",
    "report": "Submit",
    "will_quit_room":"Exit after this game",
    "agree_friend_request":"Pass verification",
    "friend_request_message":"friend request notice",
    "No_friend_message":"No friend request, go add some friend to play~",
    "disagree_friend_request":"Reject",
    "agree" : "Agree",
    "agreed" : "Agreed",
    "send_friend_message":"Send Message",
    "delete_friend":"Delete Friend",
    "Search_Friend":"Search Friend",
    "Input_Friends_Nickname":"     Input friend nickname",
    "Received_picture":"received picture",
    "Received_voice":"received voice",
    "request_add_friend":"Request to be friend",
    "add_friend":"Add Firend",
    "report_type":"Report Type",
    "next":"Next",
    "report_back":"Report and feedback",
    "report":"Submit",
    "select_pic":"Please provide evidence with picture",
    "YooBa":"NiceHand",
    "GoodHand":"NiceHand",
    "Copyright© 2015 ":"Copyright Beijing ChinaRich inc.",
    "decrip_hoder":"Please provide your claim or feedback",
    "decrip_moment":"Sharing is a good thing...",
    "sharemoment":"share",
    "commentmoment":"comment",
    "game_hint":"No games? try to setup one in club or swip right",
    "chat_alert":"Too much words, try another line?",
    "half_pot":"1/2 Pot",
    "twothirds_pot":"2/3 Pot",
    "full_pot":"Full Pot",
    "request_to_be_friend":"Requests to be your friend",
    "applying_group":"requests to join  ",
    "group":"group",
    "inviting_you_to_join":"  invites you to join  ",
    "rejected":"refused",
    "agreed":"agreed",
    "2_points_minimum":" 2 points needed",
    "3_points_award":" 3 points award",
    "to_self":"For myself",
    "to_all":"For everyone",
    "to_friends":"For friends",
    "current_players":"Players：",
    "total_chips":"Total Chips：",
    "average_chips":"Average Chips：",
    "Addon_no_rebuy":"Addon：No re-entry",
    "Addon_rebuy_amount":"Addon：re-entry（rebuy:",
    "current_level":"current level：",
    "game_time":"Game time：",
    "mvp":"MVP",
    "bigfish":"BigFish",
    "highestbuyin":"BuyIn",
    "total_profit":"Total Profit",
    "average_profit":"Average Game Profit",
    "NA":"Not Available",
    "total_profit":"",
    "per_hour_profit":"Hour Profit",
    "per_100_profit":"100-hand Profit",
    "average_game_profit":"Average game profit",
    "tournament_name":"Tournament Name",
    "SNG_name":"SNG Name",
    "score":"score",
    "player_sitting_out":"Player Sitout",
    "waiting_for_next_game":"Wait for next game",
    "leaving_soon":"Leaving soon",
    "extra_award":"Extra award：",
    "player_standing_up":"Player stand up",
    "player_leave":"player leave",
    "texas_comment":"Texas Holdem comment",
    "starting_at":"start time：",
    "first_moment":"say something",
    "shared":"Shared",
    "disconnect":"Allow us to re-connect...",
    "to_continue_addon":"To continue, rebuy: ",
    "continue_tournament_ornot":"Continue?",
    "enter_room":"Enter Room",
    "quick_access_create_room":"Create Room",
    "quick_access_title":"Nice Hand",
    "quick_access_room_tip":"Please input room number",
    "usersetting_title":"Settings",
    "name_tip":"Nickname：",
    "diamond_tip":"Diamond：",
    "stamina_tip":"HealthPoint：",
    "usersetting_bind_phone":"Bind",
    "usersetting_bind_phone_change":"Change",
    "usersetting_buy_diamond":"Charge",
    "usersetting_charge_stamina":"Get",
    "usersetting_record_layer":"Performance",
    "usersetting_share_layer":"Share",
    "usersetting_game_setting":"Game Settings",
    "woman":"♀",
    "man":"♂",
    "change_password":"Change Password",
    "exit_game":"Logout",
    "user_response":"Feedback",
    "nickname_change":"Modify",
    "nickname_save":"Save",
    "not_bind_phone":"Not yet bind",
    "bind_phone_tip":"Cell：",
    "bind_phone":"Bind",
    "bind_phone_cancle":"Cancel",
    "bind_phone_verification":"Verify Code",
    "take_photos":"Take Photo",
    "choose_photo_native":"Album",
    "exit_choose_layer":"Cancel",
    "confirm_change_password":"OK",
    "cancle_change_password":"Cancel",
    "title_club":"Club",
    "disconnect":"Offline",
    "current_month":"Current Month",
    "block_his_moment": "Block moment",
    "block_her_moment": "Block Moment",
    "Mall":"Mall",
    "diamond":"Diamond",
    "self_charge":"No friend, please buy for yourself",
    "buy_ok":"Purchase Complete",
    "wait_for_previous_transaction": "Please wait for previous transaction done",
    "wait_for_charge":"Initiating purchase, please wait",
    "payable": "Payable",
    "Health_point": "HP：",
    "Buy":"Buyin：",
    "order_list":"Order List",
    "playground":"Playground",
    "room_empty":"Room number cannot be empty",
    "whole_number":"Room number should be whole number",
    "Time range": "Time range：in 7 days",
    "describe_qus":"Describe your question",
    "logout_confirm":"Are you sure to logout?",
    "create_club":"Create club",
    "input_club_account": "Input club‘s name",
    "input_club_remarks":"Input club‘s remarks",
    "add_phone_contacts":"Add phone contacts",
    "select_type":"Select game type",
    "remark":"remark",
    "minutes":"minutes",
    "no_phone_contact":"can't found phone contacts",
    "remark":"Remark:",
    "minutes":"minutes",
    "system_setting":"System Setting",
    "more_setting":"More Setting",
    "simple_setting":"Simple Setting",
    "delete_successed":"Delete successed",
    "delete_failed":"Delete failed",
    "remark_failed":"Make remarks failed",
    "publish_failed":"Publish failed",
    "charge_for_self":"Charge for yourself",
    "charge_for_others":"Charge for others",
    "charge_failed":"Charge failed，please resend the message",
    "charging":"Charging,please wait for a moment",
    "nickname":"Nickname",
    "personal_info":"Personal information",
    "phone_contacts":"Phone Contacts",
    "players":"Players",
    "scores":"Scores",
    "present_records":"Present Records",
    "none":"None",
    "quit_club":"Are you sure to quit/disband the club?",
    "club_management":"Club Management",
    "show_player_records":"Show Records",
    "my_redit":"My credit",
    "club_share":"Club Share",
    "no_message":"No message",
    "clear_mes_record":"Clear chat logs",
    "quit_group":"Quit/disban group",
    "gametype":"Gametype",
    "remaining_time":"Remainingtime",
    "choose_room":"Choose Room",
    "public_rank":"Public Rank",
    "accomplished":"Accomplished",
    "club_inviting":"Club Inviting",
    "ask_enter_club":"Ask to enter club",
    "invite_enter_club":"Invite you to join the club",
    "account_exist":"The account does not exist",
    "delete_friend_successed":"Delete friend successed",
    "delete_friend_failed":"Delete friend failed",
    "operate_failed":"Operate failed",
    "set_contacts":"You do not open Haopai to set contacts,please go to Privacy-Contacts-Haopai to set function!",
    "add":"Add",
    "invite":"Invite",
    "total_number":"Total numbers",
    "total_buy_chip":"Total chips",
    "no_players":"This room has no players,\nand has no records.",
    "from":"from",
    "input_whole":"Your input should be whole number.",
    "give_diamond":"Give diamonds",
    "game_name":"Game Name",
     "price_rewards":"Awards",
     "ranking":"Ranking",
     "bonus":"Bonus%",
     "extra_bonus":"Extra Bonus",
     "to":" To ",
     "strart_rank":"From",
     "rankend":"",
     "delete":"Delete",
     "create_no_club":"You cannot create room in official club",
     "operate_successed":"Operate successed",
     "desk_num":"Desk Number",
     "join":"Join",
     "other_info":"Other information",
     "get_setMsg_failed":"Getting verify code failed.",
     "time":"Time",
     "change_password_successed":"Change passwords successed",
     "terms_of_use_and_privacy_policy":"Terms of use and privacy policy",
     "language_format":"Only support Chinese, English, Numbers, and underscores",
     "support_number":"Only support numbers",
     "sure_to_delete":"Are you sure to delete it?",
     "nono_group":"(None group)",
     "replay":"Replay",
     "all_scores":"All scores",
     "new_version":"There is a new version of this game,do you want to update or not?",
     "offer_chip":"There will be some chips after this hands",
     "too_many_info":"You input is too many,please input again!",
     "refresh_failed":"Refresh friends list failed!",
     "new_version_and_update":"There is a new version of this game,please update",
     "kick_off_players":"Kick off the player or not?",
     "request_timed_out":"Request timed out",
     "operate_failed_retry":"Operate failed,please retry!",
     "choose_club":"Choose Club",
     "take_a_share":"Take a share",
     "auto_check_cards":"Auto\nCheck",
     "auto_call_raise":"Call",
     "choose_language":"Choose Language",
     "replay_audio":"Replay",
     "kick_out":"Kick out",
     "virtual_props":"Virtual Props",
     "HP_prop":"You need 30 Hp to use this prop",
     "reconnect":"Reconnecting",
     "standing_up":"Stand Up",
     "leave":"Sit out",
     "wait":"waiting",
     "fold":"Fold",
     "check":"Check",
     "bet":"Bet",
     "raise":"Raise",
     "all_in":"All In",
     "change_langage":"Sure to change\npresent language？",
     "return_credit":"Return credit",
     "allow_check_club_member":"Allow player to check member's info",
     "mute":"Make club members mute",
     "group_advocate":"Group advocate's rights",
     "need_full":"SNG",
    "rewards_pool":"Pond Rate",
    "registration_fee":"Registration fee",
    "operate_time":"Operate time",
    "PlayerPerTable":"Full commission number",
    "TemplateSize":"Scale",
    "TemplateSpeed":"Speed",
    "the_Blinds_level":"the Blinds Level",
    "pond_details":"Pond Details",
    "small_blind":"Small Blind",
    "big_blind":"Big Blind",
    "chatch":"Straddle",
    "call":"Call",
    "sit_back":"Sit",
    "follow_or_give_up":"Check/\nFold",
    "continue":"Continue",
    "licensing_twice":"Licensing \ntwice",
    "agree_license_twice":"Agree License Twice",
    "disagrees_license_twice":"Disagree License Twice",
    "check_peseronal_info":"Check member's info",
    "set_admin":"Set Administrator",
    "set_credit_amount":"Set credit amount",
    "check_info":"Check",
    "only_group_advocate":"Only group advocate are authorized to do so!",
    "request_has_aready_send":"Request has aready beensent!",
    "request_failed":"Request failed!",
    "give_successfully":"Give successfully!",
    "shre_failed":"Share function cannot be used at this time!",
    "leave_room":"Leave",
    "reset_cards":"Reset Cards",
    "head":"Head row",
    "middle":"Midr ow",
    "botton":"Bottom row",
    "color":"Color",
    "pair":"Pairs",
    "order":"Order",
    "royal_and_flush":"Royal\nFlush",
    "straight_flush_":"Straight\nFlush",
    "full_house":"Full\nHouse",
    "two_pairs":"Two\nPairs",
    "three_of_kind":"Three\nof\nKind",
    "straight":"Straight",
    "four_of_kind":"Four\nof\nKind",
    "flush":"Flush",
    "one_pair":"One\nPair",
    "raise_free":"raise\nfree",
    "bet_free":"bet\nfree",
    "game_pause":"Game paused,",
    "please_wait":"please wait...",
    "year":"-",
    "month":"-",
    "day":"-",
    "minute":"-",
    "second":"-",
    "hour":"-",
    "flop":"Flop",
    "turn":"Turn",
    "river":"River",
    "win":"Win",
    "hours":"hours",
    "clud_mute":"Only group advocate and admin can speak right now.",
    "android_click_back":"Press again to exit the application",
    "no_speak":"This player has not spoken!",
    "no_credit":"You do not have enough credit!",
    "player_rank_is_null":"Dear,you don't have rank records,go and play with your frends!",
    "not_open_player_rank":"Club admin doesn't disclose user's rank.",
    "send_message_faild":"Sending message failure，please check your Internat or resend message.",
    "account_format":"Account should be letter or number.",
    "account_too_long":"Account is too long,it should be in 15 letters",
    "passwords_too_long":"Passwords is too long,it should be in 15 letters",
    "bind_cell":"If you need bind cellphone ,please input the phonenumber!",
    "bind_cell_vertify":"If you need bind cellphone ,please input the verficiation code!",
    "input_vertify":"Please input the verficiation code",
    "muck":"Muck",
    "text_search":"Search",
    "sichuan_mahjong":"SiChuan Mahjong",
    "friends_circle":"Moments",
    "pubnish_success":"Publish successed!",
    "pubnish_failed":"Publish failed!",
    "mahjong_water_desc":"The Bureau of the win：",
    "published_circle":"Publish Circle of Friends",
    "choose_handID":"Choose Hand Poker",
    "gongkai":"Public(All friends can see)",
    "simi":"Private（Only visible to yourself）",
    "please_input":"Please input your info",
    "veri_code_choose":"Verify Code(Optional)",
    "mahjong_water_desc":"The Bureau of the win：",
    "mahjong_auto_card":"自动\n胡牌",
    "mahjong_auto_play":"自动\n打牌",
    "left_pos":"上家",
    "right_pos":"下家",
    "opposite_pos":"對家",
    "self_pos":"三家",
    "mahjong_no_user":"现在还没有玩家哦",
    "mahjong_win_type":["平胡","对对胡","清一色","带幺九","七对","金钓钓","清对","将对","龙七对","清七对","清幺九","清金钓钓","将金钓钓","天胡","地胡","青龙七对","十八罗汉","杠开","杠上炮","根","抢杠","自摸","刮风","刮风","下雨","呼叫转移","退税","查大叫","查花猪","被自摸","点炮","被刮风","被下雨","被呼叫转移","被查花猪","被查大叫","被退税"],
    "empty_punishifo":"Publish info should not be empty!",
    "send":"Send",
    "input_info":"Please input your info",
    "reply":"Reply",
    "delete_Moment":"Are you sure to delete this moment?",
    "delete_comment":"Are you sure to delete this comment?",
    "delete_support":"Are you sure to cancel this support?",
    "cancle_game":"Cancel game",
    "game_info":"Competition info"






}